ceramic_python/__init__.py
ceramic_python/ceramic_client.py
ceramic_python/did.py
ceramic_python/helper.py
ceramic_python/model_instance_document.py
ceramic_python-0.1.7.dist-info/METADATA
ceramic_python-0.1.7.dist-info/WHEEL
ceramic_python-0.1.7.dist-info/top_level.txt
ceramic_python-0.1.7.dist-info/RECORD
