Metadata-Version: 2.1
Name: ceramic_python
Version: 0.1.7
Summary: This Ceramic client implements the payload building, encoding, and signing needed to interact with the Ceramic Network. It currently supports ModelInstanceDocument.
Home-page: https://github.com/indexnetwork/ceramic-python/tree/main/ceramic-client
Author: Index
Author-email: accounts@index.network
Classifier: Development Status :: 3 - Alpha
Classifier: Intended Audience :: Developers
Classifier: License :: OSI Approved :: MIT License
Classifier: Programming Language :: Python :: 3
Classifier: Programming Language :: Python :: 3.7
Classifier: Programming Language :: Python :: 3.8
Classifier: Programming Language :: Python :: 3.9
Requires-Python: >=3.7
Requires-Dist: requests ==2.31.0
Requires-Dist: python-dateutil ==2.8.2
Requires-Dist: pytz ==2023.3
Requires-Dist: jsonpatch ==1.33
Requires-Dist: cryptography ==41.0.1
Requires-Dist: jwcrypto ==1.5.0
Requires-Dist: multiformats ==0.3.1
Requires-Dist: dag-cbor ==0.3.2
Requires-Dist: base58 ==2.1.1
